psy_simple/__init__.py
psy_simple/_version.py
psy_simple/base.py
psy_simple/colors.py
psy_simple/plotters.py
psy_simple/plugin.py
psy_simple/widgets/__init__.py
psy_simple/widgets/colors.py
psy_simple/widgets/texts.py
psy_simple/widgets/icons/bold.png
psy_simple/widgets/icons/font_color.png
psy_simple/widgets/icons/italic.png
psy_simple/widgets/icons/cmaps/Accent.png
psy_simple/widgets/icons/cmaps/Accent_r.png
psy_simple/widgets/icons/cmaps/Blues.png
psy_simple/widgets/icons/cmaps/Blues_r.png
psy_simple/widgets/icons/cmaps/BrBG.png
psy_simple/widgets/icons/cmaps/BrBG_r.png
psy_simple/widgets/icons/cmaps/BuGn.png
psy_simple/widgets/icons/cmaps/BuGn_r.png
psy_simple/widgets/icons/cmaps/BuPu.png
psy_simple/widgets/icons/cmaps/BuPu_r.png
psy_simple/widgets/icons/cmaps/CMRmap.png
psy_simple/widgets/icons/cmaps/CMRmap_r.png
psy_simple/widgets/icons/cmaps/Dark2.png
psy_simple/widgets/icons/cmaps/Dark2_r.png
psy_simple/widgets/icons/cmaps/GnBu.png
psy_simple/widgets/icons/cmaps/GnBu_r.png
psy_simple/widgets/icons/cmaps/Greens.png
psy_simple/widgets/icons/cmaps/Greens_r.png
psy_simple/widgets/icons/cmaps/Greys.png
psy_simple/widgets/icons/cmaps/Greys_r.png
psy_simple/widgets/icons/cmaps/OrRd.png
psy_simple/widgets/icons/cmaps/OrRd_r.png
psy_simple/widgets/icons/cmaps/Oranges.png
psy_simple/widgets/icons/cmaps/Oranges_r.png
psy_simple/widgets/icons/cmaps/PRGn.png
psy_simple/widgets/icons/cmaps/PRGn_r.png
psy_simple/widgets/icons/cmaps/Paired.png
psy_simple/widgets/icons/cmaps/Paired_r.png
psy_simple/widgets/icons/cmaps/Pastel1.png
psy_simple/widgets/icons/cmaps/Pastel1_r.png
psy_simple/widgets/icons/cmaps/Pastel2.png
psy_simple/widgets/icons/cmaps/Pastel2_r.png
psy_simple/widgets/icons/cmaps/PiYG.png
psy_simple/widgets/icons/cmaps/PiYG_r.png
psy_simple/widgets/icons/cmaps/PuBu.png
psy_simple/widgets/icons/cmaps/PuBuGn.png
psy_simple/widgets/icons/cmaps/PuBuGn_r.png
psy_simple/widgets/icons/cmaps/PuBu_r.png
psy_simple/widgets/icons/cmaps/PuOr.png
psy_simple-1.5.1.dist-info/CC-BY-4.0.txt
psy_simple-1.5.1.dist-info/CC0-1.0.txt
psy_simple-1.5.1.dist-info/LGPL-3.0-only.txt
psy_simple-1.5.1.dist-info/METADATA
psy_simple-1.5.1.dist-info/WHEEL
psy_simple-1.5.1.dist-info/entry_points.txt
psy_simple-1.5.1.dist-info/top_level.txt
psy_simple-1.5.1.dist-info/RECORD
