Metadata-Version: 2.1
Name: psy-simple
Version: 1.5.1
Summary: Psyplot plugin for simple visualization tasks
Author-email: "Philipp S. Sommer" <philipp.sommer@hereon.de>
Maintainer-email: "Philipp S. Sommer" <philipp.sommer@hereon.de>
License: LGPL-3.0-only
Project-URL: Homepage, https://codebase.helmholtz.cloud/psyplot/psy-simple
Project-URL: Documentation, https://psyplot.github.io/psy-simple
Project-URL: Source, https://codebase.helmholtz.cloud/psyplot/psy-simple
Project-URL: Tracker, https://codebase.helmholtz.cloud/psyplot/psy-simple/issues/
Keywords: visualization,psyplot,netcdf,matplotlib
Classifier: Development Status :: 5 - Production/Stable
Classifier: Intended Audience :: Developers
Classifier: Topic :: Scientific/Engineering :: Visualization
Classifier: Topic :: Scientific/Engineering :: GIS
Classifier: Topic :: Scientific/Engineering
Classifier: License :: OSI Approved :: GNU Lesser General Public License v3 (LGPLv3)
Classifier: Programming Language :: Python :: 3
Classifier: Programming Language :: Python :: 3 :: Only
Classifier: Programming Language :: Python :: 3.7
Classifier: Programming Language :: Python :: 3.8
Classifier: Programming Language :: Python :: 3.9
Classifier: Programming Language :: Python :: 3.10
Classifier: Programming Language :: Python :: 3.11
Classifier: Programming Language :: Python :: 3.12
Classifier: Operating System :: OS Independent
Requires-Python: >=3.9
License-File: LICENSES/CC-BY-4.0.txt
License-File: LICENSES/CC0-1.0.txt
License-File: LICENSES/LGPL-3.0-only.txt
Requires-Dist: psyplot >=1.5.0
Requires-Dist: matplotlib >=2.0
Provides-Extra: dev
Requires-Dist: psy-simple[testsite] ; extra == 'dev'
Requires-Dist: psy-simple[docs] ; extra == 'dev'
Requires-Dist: PyYAML ; extra == 'dev'
Requires-Dist: types-PyYAML ; extra == 'dev'
Provides-Extra: docs
Requires-Dist: psy-simple[gui] ; extra == 'docs'
Requires-Dist: autodocsumm ; extra == 'docs'
Requires-Dist: sphinx-rtd-theme ; extra == 'docs'
Requires-Dist: hereon-netcdf-sphinxext ; extra == 'docs'
Requires-Dist: sphinx-design ; extra == 'docs'
Requires-Dist: ipython ; extra == 'docs'
Requires-Dist: pickleshare ; extra == 'docs'
Requires-Dist: seaborn ; extra == 'docs'
Requires-Dist: dask ; extra == 'docs'
Requires-Dist: netCDF4 ; extra == 'docs'
Provides-Extra: gui
Requires-Dist: psyplot-gui ; extra == 'gui'
Provides-Extra: testsite
Requires-Dist: tox ; extra == 'testsite'
Requires-Dist: isort ==5.12.0 ; extra == 'testsite'
Requires-Dist: black ==23.1.0 ; extra == 'testsite'
Requires-Dist: flake8 ==6.0.0 ; extra == 'testsite'
Requires-Dist: pre-commit ; extra == 'testsite'
Requires-Dist: mypy ; extra == 'testsite'
Requires-Dist: pytest-cov ; extra == 'testsite'
Requires-Dist: reuse ; extra == 'testsite'
Requires-Dist: cffconvert ; extra == 'testsite'
Requires-Dist: pytest-xdist ; extra == 'testsite'
Requires-Dist: dask ; extra == 'testsite'
Requires-Dist: netCDF4 ; extra == 'testsite'
Requires-Dist: seaborn ; extra == 'testsite'
Requires-Dist: statsmodels ; extra == 'testsite'
Requires-Dist: psyplot-gui ; extra == 'testsite'
